fezzypixels/__init__.py
fezzypixels/blend.py
fezzypixels/color.py
fezzypixels/helper.py
fezzypixels/shift.py
fezzypixels/error_diffuse/__init__.py
fezzypixels/error_diffuse/diffusion_dither.py
fezzypixels/error_diffuse/diffusion_weights.py
fezzypixels/error_diffuse/lab_err_diff.c
fezzypixels/error_diffuse/lab_err_diff.cp312-win_amd64.pyd
fezzypixels/error_diffuse/lab_err_diff.pyx
fezzypixels/palette/__init__.py
fezzypixels/palette/color_compare.py
fezzypixels/palette/k_means.c
fezzypixels/palette/k_means.cp312-win_amd64.pyd
fezzypixels/palette/k_means.pyx
fezzypixels/palette/k_means_minibatch_lab.py
fezzypixels/palette/k_means_refine.py
fezzypixels/palette/median_cut.py
fezzypixels/palette/preprocess.py
fezzypixels/pattern/HDR_L_0.png
fezzypixels/pattern/__init__.py
fezzypixels/pattern/bayer.py
fezzypixels/pattern/fast_candidates.c
fezzypixels/pattern/fast_candidates.cp312-win_amd64.pyd
fezzypixels/pattern/fast_candidates.pyx
fezzypixels/pattern/pattern_dither.py
fezzypixels/preprocess/HDR_L_1.png
fezzypixels/preprocess/__init__.py
fezzypixels/preprocess/ordered_pattern_dither_srgb.py
fezzypixels-0.0.1.dist-info/LICENSE
fezzypixels-0.0.1.dist-info/METADATA
fezzypixels-0.0.1.dist-info/WHEEL
fezzypixels-0.0.1.dist-info/top_level.txt
fezzypixels-0.0.1.dist-info/RECORD
