Metadata-Version: 2.1
Name: fezzypixels
Version: 0.0.1
Summary: High-quality RGB555 dithering and paletting library
Author: bullbin
License: MIT License
Project-URL: Homepage, https://github.com/bullbin/fezzypixels
Project-URL: Repository, https://github.com/bullbin/fezzypixels.git
Project-URL: Issues, https://github.com/bullbin/fezzypixels/issues
Classifier: Development Status :: 3 - Alpha
Classifier: Intended Audience :: Developers
Classifier: License :: OSI Approved :: MIT License
Classifier: Programming Language :: Python :: 3 :: Only
Classifier: Topic :: Artistic Software
Classifier: Topic :: Multimedia :: Graphics
Classifier: Topic :: Multimedia :: Graphics :: Graphics Conversion
License-File: LICENSE
Requires-Dist: numpy~=2.1.3
Requires-Dist: opencv-python~=4.10.0.84
Requires-Dist: scikit-learn~=1.5.2
Requires-Dist: scikit-image~=0.24.0
